{
	"boxes":
	[
		{
			"x":0.0,
			"y":180.0,
			"color":"blue",
			"shade":"zero",
			"gravity":"false",
			"m0":"none",
			"m1":"none",
			"m2":"none",
			"m3":"none"
		},
		{
			"x":120.0,
			"y":180.0,
			"color":"blue",
			"shade":"zero",
			"gravity":"false",
			"m0":"none",
			"m1":"none",
			"m2":"none",
			"m3":"none"
		},
		{
			"x":240.0,
			"y":180.0,
			"color":"blue",
			"shade":"zero",
			"gravity":"false",
			"m0":"none",
			"m1":"none",
			"m2":"none",
			"m3":"none"
		},
		{
			"x":360.0,
			"y":180.0,
			"color":"blue",
			"shade":"zero",
			"gravity":"false",
			"m0":"none",
			"m1":"none",
			"m2":"none",
			"m3":"none"
		},
		{
			"x":1800.0,
			"y":0.0,
			"color":"yellow",
			"shade":"eight",
			"gravity":"false",
			"m0":"up",
			"m1":"none",
			"m2":"none",
			"m3":"none"
		}
	],
	"triangles":
	[
	],
	"goals":
	[
		{
			"x":0.0,
			"y":300.0
		}
	],
	"doors":
	[
	],
	"switches":
	[
	],
	"mines":
	[
	],
	"guns":
	[
		{
			"x":50.0,
			"y":50.0,
			"id":0
		},
	],
	"startgun":0
}
